{
  "schema_version": "1.0",
  "server": {
    "name": "cesarmoreno-portfolio",
    "description": "Cesar Moreno's portfolio — Full Stack Engineer · AI. Query professional data via MCP protocol.",
    "url": "https://cesarmoreno.dev/api/mcp",
    "transport": "streamable-http",
    "protocol_version": "2024-11-05"
  },
  "capabilities": {
    "tools": true
  },
  "tools": [
    {
      "name": "get_about",
      "description": "Get Cesar Moreno's professional bio, role, highlights, and contact links"
    },
    {
      "name": "get_experience",
      "description": "Get work experience timeline with roles, companies, and technologies"
    },
    {
      "name": "get_projects",
      "description": "Get featured and archived projects with descriptions, tech stack, and links"
    },
    {
      "name": "get_tech_stack",
      "description": "Get technology expertise organized by category"
    }
  ],
  "contact": {
    "github": "https://github.com/cmorenogit",
    "linkedin": "https://linkedin.com/in/morenodev"
  }
}
